odoo/addons/account_invoice_bank_brand/README.rst
odoo/addons/account_invoice_bank_brand/__init__.py
odoo/addons/account_invoice_bank_brand/__manifest__.py
odoo/addons/account_invoice_bank_brand/i18n/account_invoice_bank_brand.pot
odoo/addons/account_invoice_bank_brand/i18n/it.po
odoo/addons/account_invoice_bank_brand/i18n/nl.po
odoo/addons/account_invoice_bank_brand/models/__init__.py
odoo/addons/account_invoice_bank_brand/models/account_move.py
odoo/addons/account_invoice_bank_brand/models/res_brand.py
odoo/addons/account_invoice_bank_brand/readme/CONTRIBUTORS.md
odoo/addons/account_invoice_bank_brand/readme/DESCRIPTION.md
odoo/addons/account_invoice_bank_brand/readme/USAGE.md
odoo/addons/account_invoice_bank_brand/static/description/icon.png
odoo/addons/account_invoice_bank_brand/static/description/index.html
odoo/addons/account_invoice_bank_brand/tests/__init__.py
odoo/addons/account_invoice_bank_brand/tests/test_account_move.py
odoo/addons/account_invoice_bank_brand/views/res_brand.xml
odoo_addon_account_invoice_bank_brand-18.0.1.0.0.6.dist-info/METADATA
odoo_addon_account_invoice_bank_brand-18.0.1.0.0.6.dist-info/WHEEL
odoo_addon_account_invoice_bank_brand-18.0.1.0.0.6.dist-info/top_level.txt
odoo_addon_account_invoice_bank_brand-18.0.1.0.0.6.dist-info/RECORD
