Metadata-Version: 2.1
Name: odoo-addon-account_invoice_bank_brand
Version: 18.0.1.0.0.6
Requires-Python: >=3.10
Requires-Dist: odoo-addon-account_brand==18.0.*
Requires-Dist: odoo==18.0.*
Summary: Enables the automatic selection of the partner'sbank account on invoices based on the brand.
Home-page: https://github.com/OCA/brand
License: AGPL-3
Author: ACSONE SA/NV,Odoo Community Association (OCA)
Author-email: support@odoo-community.org
Classifier: Programming Language :: Python
Classifier: Framework :: Odoo
Classifier: Framework :: Odoo :: 18.0
Classifier: License :: OSI Approved :: GNU Affero General Public License v3
